LICENSE
MANIFEST.in
README.md
requirements.txt
setup.py
stuoe/__init__.py
stuoe/app.py
stuoe/function.py
stuoe/server.conf
stuoe/sqlite3.db
stuoe/view.py
stuoe.egg-info/PKG-INFO
stuoe.egg-info/SOURCES.txt
stuoe.egg-info/dependency_links.txt
stuoe.egg-info/entry_points.txt
stuoe.egg-info/not-zip-safe
stuoe.egg-info/requires.txt
stuoe.egg-info/top_level.txt
stuoe/CacheFile/3172219__file__
stuoe/CacheFile/6184879__file__S.png
stuoe/CacheFile/placeholder.txt
stuoe/extension/api/main.py
stuoe/extension/example/README.md
stuoe/extension/example/main.py
stuoe/migrations/README
stuoe/migrations/alembic.ini
stuoe/migrations/env.py
stuoe/migrations/script.py.mako
stuoe/public/avater.jpg
stuoe/public/index.html
stuoe/public/stuoe.css
stuoe/public/stuoe.xml
stuoe/public/jquery/AUTHORS.txt
stuoe/public/jquery/LICENSE.txt
stuoe/public/jquery/README.md
stuoe/public/jquery/bower.json
stuoe/public/jquery/package.json
stuoe/public/jquery/dist/jquery.js
stuoe/public/jquery/dist/jquery.min.js
stuoe/public/jquery/dist/jquery.min.map
stuoe/public/jquery/dist/jquery.slim.js
stuoe/public/jquery/dist/jquery.slim.min.js
stuoe/public/jquery/dist/jquery.slim.min.map
stuoe/public/jquery/external/sizzle/LICENSE.txt
stuoe/public/jquery/external/sizzle/dist/sizzle.js
stuoe/public/jquery/external/sizzle/dist/sizzle.min.js
stuoe/public/jquery/external/sizzle/dist/sizzle.min.map
stuoe/public/jquery/src/ajax.js
stuoe/public/jquery/src/attributes.js
stuoe/public/jquery/src/callbacks.js
stuoe/public/jquery/src/core.js
stuoe/public/jquery/src/css.js
stuoe/public/jquery/src/data.js
stuoe/public/jquery/src/deferred.js
stuoe/public/jquery/src/deprecated.js
stuoe/public/jquery/src/dimensions.js
stuoe/public/jquery/src/effects.js
stuoe/public/jquery/src/event.js
stuoe/public/jquery/src/jquery.js
stuoe/public/jquery/src/manipulation.js
stuoe/public/jquery/src/offset.js
stuoe/public/jquery/src/queue.js
stuoe/public/jquery/src/selector-native.js
stuoe/public/jquery/src/selector-sizzle.js
stuoe/public/jquery/src/selector.js
stuoe/public/jquery/src/serialize.js
stuoe/public/jquery/src/traversing.js
stuoe/public/jquery/src/wrap.js
stuoe/public/jquery/src/ajax/jsonp.js
stuoe/public/jquery/src/ajax/load.js
