Metadata-Version: 2.1
Name: stuoe
Version: 0.1.3.9
Summary: Lightweight forum, simple interface, easy to install
Home-page: https://stuoe.cn
Author: snbck
Author-email: snbckcode@gmail.com
License: Apache License
Platform: UNKNOWN
